emailrep/__init__.py
emailrep/cli.py
emailrep/utils.py
emailrep-0.0.5.dist-info/LICENSE
emailrep-0.0.5.dist-info/METADATA
emailrep-0.0.5.dist-info/WHEEL
emailrep-0.0.5.dist-info/entry_points.txt
emailrep-0.0.5.dist-info/top_level.txt
emailrep-0.0.5.dist-info/RECORD
