Metadata-Version: 2.1
Name: emailrep
Version: 0.0.5
Summary: Python interface for the EmailRep API
Home-page: https://emailrep.io
Author: Sublime Security
Author-email: hi@sublimesecurity.com
License: MIT
Download-URL: https://github.com/sublime-security/emailrep.io-python
Keywords: security,phishing,analysts,soc,threat intelligence
Platform: UNKNOWN
Classifier: Programming Language :: Python :: 3
Classifier: License :: OSI Approved :: MIT License
Classifier: Operating System :: OS Independent
Classifier: Natural Language :: English
Classifier: Intended Audience :: Developers
